{
    "caller-id": "03c59ba692", 
    "turns": [
        {
            "turn-index": 0, 
            "goal-labels": {
                "pricerange": "moderate", 
                "area": "east"
            }, 
            "transcription": "looking for a moderately priced restaurant in the east part of town", 
            "method-label": "byconstraints", 
            "audio-file": "pt344x_0000944_0001238.wav", 
            "requested-slots": [], 
            "semantics": {
                "json": [
                    {
                        "slots": [
                            [
                                "pricerange", 
                                "moderate"
                            ]
                        ], 
                        "act": "inform"
                    }, 
                    {
                        "slots": [
                            [
                                "area", 
                                "east"
                            ]
                        ], 
                        "act": "inform"
                    }
                ], 
                "cam": "inform(pricerange=moderate,type=restaurant,area=east)"
            }
        }, 
        {
            "turn-index": 1, 
            "goal-labels": {
                "food": "dontcare", 
                "pricerange": "moderate", 
                "area": "east"
            }, 
            "transcription": "i dont care", 
            "method-label": "byconstraints", 
            "audio-file": "pt344x_0001563_0001613.wav", 
            "requested-slots": [], 
            "semantics": {
                "json": [
                    {
                        "slots": [
                            [
                                "this", 
                                "dontcare"
                            ]
                        ], 
                        "act": "inform"
                    }
                ], 
                "cam": "inform(=dontcare)"
            }
        }, 
        {
            "turn-index": 2, 
            "goal-labels": {
                "food": "dontcare", 
                "pricerange": "moderate", 
                "area": "east"
            }, 
            "transcription": "whats the address", 
            "method-label": "byconstraints", 
            "audio-file": "pt344x_0002262_0002342.wav", 
            "requested-slots": [
                "addr"
            ], 
            "semantics": {
                "json": [
                    {
                        "slots": [
                            [
                                "slot", 
                                "addr"
                            ]
                        ], 
                        "act": "request"
                    }
                ], 
                "cam": "request(addr)"
            }
        }, 
        {
            "turn-index": 3, 
            "goal-labels": {
                "food": "dontcare", 
                "pricerange": "moderate", 
                "area": "east"
            }, 
            "transcription": "whats the phone number", 
            "method-label": "byconstraints", 
            "audio-file": "pt344x_0003074_0003157.wav", 
            "requested-slots": [
                "phone"
            ], 
            "semantics": {
                "json": [
                    {
                        "slots": [
                            [
                                "slot", 
                                "phone"
                            ]
                        ], 
                        "act": "request"
                    }
                ], 
                "cam": "request(phone)"
            }
        }, 
        {
            "turn-index": 4, 
            "goal-labels": {
                "food": "dontcare", 
                "pricerange": "moderate", 
                "area": "east"
            }, 
            "transcription": "whats the post code", 
            "method-label": "byconstraints", 
            "audio-file": "pt344x_0003964_0004033.wav", 
            "requested-slots": [
                "postcode"
            ], 
            "semantics": {
                "json": [
                    {
                        "slots": [
                            [
                                "slot", 
                                "postcode"
                            ]
                        ], 
                        "act": "request"
                    }
                ], 
                "cam": "request(postcode)"
            }
        }, 
        {
            "turn-index": 5, 
            "goal-labels": {
                "food": "dontcare", 
                "pricerange": "moderate", 
                "area": "east"
            }, 
            "transcription": "thank you good bye", 
            "method-label": "finished", 
            "audio-file": "pt344x_0004731_0004810.wav", 
            "requested-slots": [], 
            "semantics": {
                "json": [
                    {
                        "slots": [], 
                        "act": "thankyou"
                    }, 
                    {
                        "slots": [], 
                        "act": "bye"
                    }
                ], 
                "cam": "thankyou()|bye()"
            }
        }
    ], 
    "task-information": {
        "goal": {
            "text": "Task 00393: You are looking for a moderately priced restaurant and it should be in the east part of town. You want to know the address, phone number, and postcode.", 
            "request-slots": [
                "addr", 
                "phone", 
                "postcode"
            ], 
            "constraints": [
                [
                    "pricerange", 
                    "moderate"
                ], 
                [
                    "area", 
                    "east"
                ]
            ]
        }, 
        "feedback": {
            "questionnaire": [
                [
                    "The system understood me well.", 
                    "strongly agree"
                ]
            ], 
            "comments": null, 
            "success": true
        }
    }, 
    "session-id": "voip-03c59ba692-20130325_180735"
}